trulens/providers/huggingface/__init__.py
trulens/providers/huggingface/endpoint.py
trulens/providers/huggingface/provider.py
trulens/providers/huggingface/py.typed
trulens_providers_huggingface-2.5.3.dist-info/METADATA
trulens_providers_huggingface-2.5.3.dist-info/WHEEL
trulens_providers_huggingface-2.5.3.dist-info/RECORD
